{
    "bookTitle": "Example book title",
    "chapters": [
        {
            "chapterTitle": "Example chapter",
            "paragraphs": [
                [
                    {
                        "th": "ตัวอย่างประโยคคำต่อคำ",
                        "en": "Example sentence word by word"
                    },
                    {
                        "th": "ตัวอย่างประโยคคำต่อคำ",
                        "en": "Example sentence word by word"
                    }
                ],
                [
                    {
                        "th": "ตัวอย่างประโยคคำต่อคำ",
                        "en": "Example sentence word by word"
                    },
                    {
                        "th": "ตัวอย่างประโยคคำต่อคำ",
                        "en": "Example sentence word by word"
                    }
                ]
            ]
        },
        {
            "chapterTitle": "Example chapter 2",
            "paragraphs": [
                [
                    {
                        "th": "ตัวอย่างประโยคคำต่อคำ",
                        "en": "Example sentence word by word"
                    },
                    {
                        "th": "ตัวอย่างประโยคคำต่อคำ",
                        "en": "Example sentence word by word"
                    }
                ],
                [
                    {
                        "th": "ตัวอย่างประโยคคำต่อคำ",
                        "en": "Example sentence word by word"
                    },
                    {
                        "th": "ตัวอย่างประโยคคำต่อคำ",
                        "en": "Example sentence word by word"
                    }
                ]
            ]
        }
    ]
}